alibabacloud_das20200116/__init__.py
alibabacloud_das20200116/client.py
alibabacloud_das20200116/models/__init__.py
alibabacloud_das20200116/models/_add_hdminstance_request.py
alibabacloud_das20200116/models/_add_hdminstance_response.py
alibabacloud_das20200116/models/_add_hdminstance_response_body.py
alibabacloud_das20200116/models/_create_cache_analysis_job_request.py
alibabacloud_das20200116/models/_create_cache_analysis_job_response.py
alibabacloud_das20200116/models/_create_cache_analysis_job_response_body.py
alibabacloud_das20200116/models/_create_cloud_bench_tasks_request.py
alibabacloud_das20200116/models/_create_cloud_bench_tasks_response.py
alibabacloud_das20200116/models/_create_cloud_bench_tasks_response_body.py
alibabacloud_das20200116/models/_create_diagnostic_report_request.py
alibabacloud_das20200116/models/_create_diagnostic_report_response.py
alibabacloud_das20200116/models/_create_diagnostic_report_response_body.py
alibabacloud_das20200116/models/_create_kill_instance_session_task_request.py
alibabacloud_das20200116/models/_create_kill_instance_session_task_response.py
alibabacloud_das20200116/models/_create_kill_instance_session_task_response_body.py
alibabacloud_das20200116/models/_create_kill_instance_session_task_with_maintain_user_request.py
alibabacloud_das20200116/models/_create_kill_instance_session_task_with_maintain_user_response.py
alibabacloud_das20200116/models/_create_kill_instance_session_task_with_maintain_user_response_body.py
alibabacloud_das20200116/models/_create_latest_dead_lock_analysis_request.py
alibabacloud_das20200116/models/_create_latest_dead_lock_analysis_response.py
alibabacloud_das20200116/models/_create_latest_dead_lock_analysis_response_body.py
alibabacloud_das20200116/models/_create_query_optimize_tag_request.py
alibabacloud_das20200116/models/_create_query_optimize_tag_response.py
alibabacloud_das20200116/models/_create_query_optimize_tag_response_body.py
alibabacloud_das20200116-2.11.2.dist-info/LICENSE
alibabacloud_das20200116-2.11.2.dist-info/METADATA
alibabacloud_das20200116-2.11.2.dist-info/WHEEL
alibabacloud_das20200116-2.11.2.dist-info/top_level.txt
alibabacloud_das20200116-2.11.2.dist-info/RECORD
